shareds-0.5.2.dist-info/METADATA
shareds-0.5.2.dist-info/WHEEL
shareds-0.5.2.dist-info/entry_points.txt
shareds/__init__.py
shareds/apply.py
shareds/base.py
shareds/loader.py
shareds/realds.py
shareds/transforms.py
shareds/utils.py
shareds/v1/cls10.py
shareds/v1/dataset/__init__.py
shareds/v1/dataset/encode.py
shareds/v1/dataset/funcs.py
shareds/v1/dataset/lmdb.py
shareds/v1/loader.py
shareds/v1/transforms.py
shareds/v1/valid.py
shareds/v2/__init__.py
shareds/v2/loader.py
shareds/verify.py
shareds/with_empty.py
shareds-0.5.2.dist-info/RECORD
