Metadata-Version: 2.1
Name: shareds
Version: 0.5.2
Summary: Shared dataset repository for meter reading
Author-Email: svtter <svtter@qq.com>
License: MIT
Requires-Python: <4.0,>=3.9
Requires-Dist: numpy
Requires-Dist: pillow
Requires-Dist: matplotlib
Requires-Dist: meterviewer>=1.3.8
Requires-Dist: lmdb>=1.5.1
